slimWS/__init__.py
slimWS/core.py
slimWS-1.0.0rc2.dist-info/LICENSE
slimWS-1.0.0rc2.dist-info/METADATA
slimWS-1.0.0rc2.dist-info/WHEEL
slimWS-1.0.0rc2.dist-info/top_level.txt
slimWS-1.0.0rc2.dist-info/RECORD
