Metadata-Version: 2.1
Name: slimWS
Version: 1.0.0rc2
Summary: minimal WebSocket framework and works as a HTTP upgrader for slimHTTP.
Home-page: https://github.com/Torxed/slimWS
Author: Anton Hvornum
Author-email: anton@hvornum.se
License: UNKNOWN
Platform: UNKNOWN
Classifier: Programming Language :: Python :: 3.8
Classifier: License :: OSI Approved :: GNU General Public License v3 (GPLv3)
Classifier: Operating System :: POSIX
Classifier: Operating System :: Microsoft
Requires-Python: >=3.8
